.DS_Store
drf_async/__init__.py
drf_async/__version__.py
drf_async/jsonasync.py
drf_async/mixins.py
drf_async/utils.py
drf_async_ws-0.0.1.dist-info/LICENSE
drf_async_ws-0.0.1.dist-info/METADATA
drf_async_ws-0.0.1.dist-info/WHEEL
drf_async_ws-0.0.1.dist-info/top_level.txt
drf_async_ws-0.0.1.dist-info/RECORD
