Metadata-Version: 2.1
Name: drf-async-ws
Version: 0.0.1
Summary: UNKNOWN
Home-page: https://github.com/CavidRzayev/drf_channels
Author: Cavid Rzayev
Author-email: rzayev592@gmail.com
License: MIT
Platform: UNKNOWN
Classifier: Development Status :: 4 - Beta
Classifier: Intended Audience :: Developers
Classifier: License :: OSI Approved :: MIT License
Classifier: Programming Language :: Python
Classifier: Programming Language :: Python :: 3
Classifier: Programming Language :: Python :: 3.6
Classifier: Programming Language :: Python :: Implementation :: CPython
Classifier: Programming Language :: Python :: Implementation :: PyPy
Requires-Python: >=3.6.0
Requires-Dist: Django
Requires-Dist: channels
Requires-Dist: djangorestframework
Provides-Extra: test
Requires-Dist: pytest ; extra == 'test'
Requires-Dist: pytest-cov ; extra == 'test'
Requires-Dist: pytest-django ; extra == 'test'
Requires-Dist: pytest-asyncio ; extra == 'test'
